LICENSE
MANIFEST.in
README.md
requirements.txt
setup.py
bin/requester
requester/__init__.py
requester/parser.py
requester/pcap.py
requester/requester.py
requester/session.py
requester/structures.py
requester/utils.py
requester.egg-info/PKG-INFO
requester.egg-info/SOURCES.txt
requester.egg-info/dependency_links.txt
requester.egg-info/not-zip-safe
requester.egg-info/requires.txt
requester.egg-info/top_level.txt